{"nodes": [{"id": "sailpanel_component", "label": "SailPanel", "file_type": "code", "source_file": "apps/web/src/components/play/SailPanel.tsx", "source_location": null, "source_url": null, "captured_at": null, "author": null, "contributor": null}, {"id": "sailpanel_get_transition_duration", "label": "getTransitionDuration", "file_type": "code", "source_file": "apps/web/src/components/play/SailPanel.tsx", "source_location": null, "source_url": null, "captured_at": null, "author": null, "contributor": null}], "edges": [{"source": "sailpanel_component", "target": "ext_game_store", "relation": "calls", "confidence": "EXTRACTED", "confidence_score": 1.0, "source_file": "apps/web/src/components/play/SailPanel.tsx", "source_location": null, "weight": 1.0}, {"source": "sailpanel_component", "target": "ext_polar_lib", "relation": "calls", "confidence": "EXTRACTED", "confidence_score": 1.0, "source_file": "apps/web/src/components/play/SailPanel.tsx", "source_location": null, "weight": 1.0}, {"source": "sailpanel_component", "target": "ext_polar_pick_optimal_sail", "relation": "calls", "confidence": "EXTRACTED", "confidence_score": 1.0, "source_file": "apps/web/src/components/play/SailPanel.tsx", "source_location": null, "weight": 1.0}, {"source": "sailpanel_component", "target": "sailpanel_get_transition_duration", "relation": "calls", "confidence": "EXTRACTED", "confidence_score": 1.0, "source_file": "apps/web/src/components/play/SailPanel.tsx", "source_location": null, "weight": 1.0}, {"source": "sailpanel_component", "target": "ext_shared_types_sail_id", "relation": "references", "confidence": "EXTRACTED", "confidence_score": 1.0, "source_file": "apps/web/src/components/play/SailPanel.tsx", "source_location": null, "weight": 1.0}], "hyperedges": []}