{"nodes": [{"id": "dev_register_routes", "label": "registerDevRoutes", "file_type": "code", "source_file": "apps/game-engine/src/api/dev.ts", "source_location": null, "source_url": null, "captured_at": null, "author": null, "contributor": null}, {"id": "dev_reset_demo_route", "label": "POST /api/v1/dev/reset-demo", "file_type": "code", "source_file": "apps/game-engine/src/api/dev.ts", "source_location": null, "source_url": null, "captured_at": null, "author": null, "contributor": null}], "edges": [{"source": "dev_register_routes", "target": "dev_reset_demo_route", "relation": "implements", "confidence": "EXTRACTED", "confidence_score": 1.0, "source_file": "apps/game-engine/src/api/dev.ts", "source_location": null, "weight": 1.0}, {"source": "dev_reset_demo_route", "target": "manager_replace_runtimes", "relation": "calls", "confidence": "EXTRACTED", "confidence_score": 1.0, "source_file": "apps/game-engine/src/api/dev.ts", "source_location": null, "weight": 1.0}, {"source": "dev_reset_demo_route", "target": "index_create_demo_runtime", "relation": "calls", "confidence": "INFERRED", "confidence_score": 0.85, "source_file": "apps/game-engine/src/api/dev.ts", "source_location": null, "weight": 1.0}], "hyperedges": []}